azure/mixedreality/remoterendering/__init__.py
azure/mixedreality/remoterendering/_api_version.py
azure/mixedreality/remoterendering/_polling.py
azure/mixedreality/remoterendering/_remote_rendering_client.py
azure/mixedreality/remoterendering/_version.py
azure/mixedreality/remoterendering/py.typed
azure/mixedreality/remoterendering/_generated/__init__.py
azure/mixedreality/remoterendering/_generated/_configuration.py
azure/mixedreality/remoterendering/_generated/_remote_rendering_rest_client.py
azure/mixedreality/remoterendering/_generated/py.typed
azure/mixedreality/remoterendering/_generated/aio/__init__.py
azure/mixedreality/remoterendering/_generated/aio/_configuration_async.py
azure/mixedreality/remoterendering/_generated/aio/_remote_rendering_rest_client_async.py
azure/mixedreality/remoterendering/_generated/aio/operations_async/__init__.py
azure/mixedreality/remoterendering/_generated/aio/operations_async/_remote_rendering_operations_async.py
azure/mixedreality/remoterendering/_generated/models/__init__.py
azure/mixedreality/remoterendering/_generated/models/_models.py
azure/mixedreality/remoterendering/_generated/models/_models_py3.py
azure/mixedreality/remoterendering/_generated/models/_remote_rendering_rest_client_enums.py
azure/mixedreality/remoterendering/_generated/operations/__init__.py
azure/mixedreality/remoterendering/_generated/operations/_remote_rendering_operations.py
azure/mixedreality/remoterendering/_shared/__init__.py
azure/mixedreality/remoterendering/_shared/authentication_endpoint.py
azure/mixedreality/remoterendering/_shared/mixed_reality_token_credential.py
azure/mixedreality/remoterendering/_shared/mixedreality_account_key_credential.py
azure/mixedreality/remoterendering/_shared/static_access_token_credential.py
azure/mixedreality/remoterendering/_shared/aio/__init__.py
azure/mixedreality/remoterendering/_shared/aio/mixed_reality_token_credential.py
azure/mixedreality/remoterendering/_shared/aio/mixedreality_account_key_credential.py
azure_mixedreality_remoterendering-1.0.0b3.dist-info/METADATA
azure_mixedreality_remoterendering-1.0.0b3.dist-info/WHEEL
azure_mixedreality_remoterendering-1.0.0b3.dist-info/top_level.txt
azure_mixedreality_remoterendering-1.0.0b3.dist-info/RECORD
